{ "columns":20,
 "image":"..\/..\/..\/img\/maps\/baseTiles.png",
 "imageheight":640,
 "imagewidth":640,
 "margin":0,
 "name":"baseTiles",
 "spacing":0,
 "tilecount":400,
 "tileheight":32,
 "tileproperties":
    {
     "10":
        {
         "solid":true
        },
     "100":
        {
         "shake":true
        },
     "102":
        {
         "shake":true
        },
     "103":
        {
         "solid":true
        },
     "104":
        {
         "solid":true
        },
     "105":
        {
         "solid":true
        },
     "106":
        {
         "item":true,
         "name":"key_blue"
        },
     "107":
        {
         "solid":true
        },
     "108":
        {
         "solid":true
        },
     "109":
        {
         "solid":true
        },
     "11":
        {
         "solid":true
        },
     "12":
        {
         "solid":true
        },
     "121":
        {
         "toFloor":"",
         "type":"stairs"
        },
     "122":
        {
         "toFloor":"",
         "type":"stairs"
        },
     "123":
        {
         "solid":true
        },
     "124":
        {
         "solid":true
        },
     "125":
        {
         "solid":true
        },
     "126":
        {
         "solid":true
        },
     "127":
        {
         "solid":true
        },
     "129":
        {
         "solid":true
        },
     "142":
        {
         "colour":"red",
         "solid":true,
         "type":"door"
        },
     "143":
        {
         "item":true,
         "name":"key_red"
        },
     "144":
        {
         "solid":true
        },
     "145":
        {
         "solid":true
        },
     "146":
        {
         "solid":true
        },
     "147":
        {
         "solid":true
        },
     "148":
        {
         "shake":true,
         "solid":true
        },
     "160":
        {
         "toFloor":"",
         "type":"stairs"
        },
     "161":
        {
         "toFloor":"",
         "type":"stairs"
        },
     "162":
        {
         "colour":"green",
         "solid":true,
         "type":"door"
        },
     "163":
        {
         "item":true,
         "name":"key_green"
        },
     "164":
        {
         "solid":true
        },
     "165":
        {
         "solid":true
        },
     "166":
        {
         "shake":true,
         "solid":true
        },
     "167":
        {
         "shake":true,
         "solid":true
        },
     "168":
        {
         "shake":true
        },
     "180":
        {
         "toFloor":"",
         "type":"stairs"
        },
     "181":
        {
         "toFloor":"",
         "type":"stairs"
        },
     "182":
        {
         "shake":true,
         "solid":true
        },
     "184":
        {
         "shake":true,
         "solid":true
        },
     "185":
        {
         "item":true,
         "name":"skull"
        },
     "186":
        {
         "shake":true,
         "type":"grave"
        },
     "187":
        {
         "shake":true,
         "solid":true
        },
     "203":
        {
         "colour":"blue",
         "solid":true,
         "type":"door"
        },
     "204":
        {
         "colour":"red",
         "solid":true,
         "type":"door"
        },
     "205":
        {
         "colour":"green",
         "solid":true,
         "type":"door"
        },
     "206":
        {
         "item":true,
         "name":"picaxe"
        },
     "223":
        {
         "shake":true
        },
     "25":
        {
         "solid":true
        },
     "26":
        {
         "solid":true
        },
     "27":
        {
         "solid":true
        },
     "28":
        {
         "solid":true
        },
     "29":
        {
         "shake":true,
         "torch":5
        },
     "30":
        {
         "solid":true
        },
     "32":
        {
         "solid":true
        },
     "44":
        {
         "solid":true
        },
     "45":
        {
         "solid":true
        },
     "46":
        {
         "solid":true
        },
     "47":
        {
         "solid":true
        },
     "48":
        {
         "solid":true
        },
     "49":
        {
         "solid":true
        },
     "5":
        {
         "solid":true
        },
     "50":
        {
         "solid":true
        },
     "51":
        {
         "solid":true
        },
     "52":
        {
         "solid":true
        },
     "6":
        {
         "solid":true
        },
     "60":
        {
         "solid":true
        },
     "61":
        {
         "solid":true
        },
     "62":
        {
         "solid":true
        },
     "67":
        {
         "solid":true
        },
     "68":
        {
         "solid":true
        },
     "69":
        {
         "solid":true
        },
     "7":
        {
         "solid":true
        },
     "8":
        {
         "solid":true
        },
     "80":
        {
         "solid":true
        },
     "81":
        {
         "solid":true
        },
     "82":
        {
         "solid":true
        },
     "83":
        {
         "solid":true
        },
     "84":
        {
         "solid":true
        },
     "85":
        {
         "solid":true
        },
     "86":
        {
         "colour":"blue",
         "solid":true,
         "type":"door"
        },
     "87":
        {
         "solid":true
        },
     "88":
        {
         "shake":true
        },
     "89":
        {
         "solid":true
        },
     "9":
        {
         "solid":true
        }
    },
 "tilepropertytypes":
    {
     "10":
        {
         "solid":"bool"
        },
     "100":
        {
         "shake":"bool"
        },
     "102":
        {
         "shake":"bool"
        },
     "103":
        {
         "solid":"bool"
        },
     "104":
        {
         "solid":"bool"
        },
     "105":
        {
         "solid":"bool"
        },
     "106":
        {
         "item":"bool",
         "name":"string"
        },
     "107":
        {
         "solid":"bool"
        },
     "108":
        {
         "solid":"bool"
        },
     "109":
        {
         "solid":"bool"
        },
     "11":
        {
         "solid":"bool"
        },
     "12":
        {
         "solid":"bool"
        },
     "121":
        {
         "toFloor":"string",
         "type":"string"
        },
     "122":
        {
         "toFloor":"string",
         "type":"string"
        },
     "123":
        {
         "solid":"bool"
        },
     "124":
        {
         "solid":"bool"
        },
     "125":
        {
         "solid":"bool"
        },
     "126":
        {
         "solid":"bool"
        },
     "127":
        {
         "solid":"bool"
        },
     "129":
        {
         "solid":"bool"
        },
     "142":
        {
         "colour":"string",
         "solid":"bool",
         "type":"string"
        },
     "143":
        {
         "item":"bool",
         "name":"string"
        },
     "144":
        {
         "solid":"bool"
        },
     "145":
        {
         "solid":"bool"
        },
     "146":
        {
         "solid":"bool"
        },
     "147":
        {
         "solid":"bool"
        },
     "148":
        {
         "shake":"bool",
         "solid":"bool"
        },
     "160":
        {
         "toFloor":"string",
         "type":"string"
        },
     "161":
        {
         "toFloor":"string",
         "type":"string"
        },
     "162":
        {
         "colour":"string",
         "solid":"bool",
         "type":"string"
        },
     "163":
        {
         "item":"bool",
         "name":"string"
        },
     "164":
        {
         "solid":"bool"
        },
     "165":
        {
         "solid":"bool"
        },
     "166":
        {
         "shake":"bool",
         "solid":"bool"
        },
     "167":
        {
         "shake":"bool",
         "solid":"bool"
        },
     "168":
        {
         "shake":"bool"
        },
     "180":
        {
         "toFloor":"string",
         "type":"string"
        },
     "181":
        {
         "toFloor":"string",
         "type":"string"
        },
     "182":
        {
         "shake":"bool",
         "solid":"bool"
        },
     "184":
        {
         "shake":"bool",
         "solid":"bool"
        },
     "185":
        {
         "item":"bool",
         "name":"string"
        },
     "186":
        {
         "shake":"bool",
         "type":"string"
        },
     "187":
        {
         "shake":"bool",
         "solid":"bool"
        },
     "203":
        {
         "colour":"string",
         "solid":"bool",
         "type":"string"
        },
     "204":
        {
         "colour":"string",
         "solid":"bool",
         "type":"string"
        },
     "205":
        {
         "colour":"string",
         "solid":"bool",
         "type":"string"
        },
     "206":
        {
         "item":"bool",
         "name":"string"
        },
     "223":
        {
         "shake":"bool"
        },
     "25":
        {
         "solid":"bool"
        },
     "26":
        {
         "solid":"bool"
        },
     "27":
        {
         "solid":"bool"
        },
     "28":
        {
         "solid":"bool"
        },
     "29":
        {
         "shake":"bool",
         "torch":"int"
        },
     "30":
        {
         "solid":"bool"
        },
     "32":
        {
         "solid":"bool"
        },
     "44":
        {
         "solid":"bool"
        },
     "45":
        {
         "solid":"bool"
        },
     "46":
        {
         "solid":"bool"
        },
     "47":
        {
         "solid":"bool"
        },
     "48":
        {
         "solid":"bool"
        },
     "49":
        {
         "solid":"bool"
        },
     "5":
        {
         "solid":"bool"
        },
     "50":
        {
         "solid":"bool"
        },
     "51":
        {
         "solid":"bool"
        },
     "52":
        {
         "solid":"bool"
        },
     "6":
        {
         "solid":"bool"
        },
     "60":
        {
         "solid":"bool"
        },
     "61":
        {
         "solid":"bool"
        },
     "62":
        {
         "solid":"bool"
        },
     "67":
        {
         "solid":"bool"
        },
     "68":
        {
         "solid":"bool"
        },
     "69":
        {
         "solid":"bool"
        },
     "7":
        {
         "solid":"bool"
        },
     "8":
        {
         "solid":"bool"
        },
     "80":
        {
         "solid":"bool"
        },
     "81":
        {
         "solid":"bool"
        },
     "82":
        {
         "solid":"bool"
        },
     "83":
        {
         "solid":"bool"
        },
     "84":
        {
         "solid":"bool"
        },
     "85":
        {
         "solid":"bool"
        },
     "86":
        {
         "colour":"string",
         "solid":"bool",
         "type":"string"
        },
     "87":
        {
         "solid":"bool"
        },
     "88":
        {
         "shake":"bool"
        },
     "89":
        {
         "solid":"bool"
        },
     "9":
        {
         "solid":"bool"
        }
    },
 "tilewidth":32,
 "type":"tileset"
}